pyoanda/__init__.py
pyoanda/__init__.pyc
pyoanda/client.py
pyoanda/client.pyc
pyoanda/exceptions.py
pyoanda/exceptions.pyc
pyoanda/order.py
pyoanda/__pycache__/__init__.cpython-34.pyc
pyoanda/__pycache__/client.cpython-34.pyc
pyoanda/__pycache__/exceptions.cpython-34.pyc
pyoanda/tests/__init__.py
pyoanda/tests/__init__.pyc
pyoanda/tests/test_client.py
pyoanda/tests/test_order.py
pyoanda/tests/__pycache__/__init__.cpython-34.pyc
pyoanda/tests/__pycache__/test_client.cpython-27-PYTEST.pyc
pyoanda/tests/__pycache__/test_client.cpython-34-PYTEST.pyc
pyoanda/tests/test_client/__init__.py
pyoanda/tests/test_client/test_account.py
pyoanda/tests/test_client/test_fundation.py
pyoanda/tests/test_client/test_instruments.py
pyoanda/tests/test_client/test_orders.py
pyoanda/tests/test_client/test_position.py
pyoanda/tests/test_client/test_trade.py
pyoanda/tests/test_client/test_transaction.py
pyoanda/tests/test_integration/__init__.py
pyoanda/tests/test_integration/integration_test_case.py
pyoanda/tests/test_integration/test_account.py
pyoanda/tests/test_integration/test_client_fundation.py
pyoanda/tests/test_integration/test_instruments.py
pyoanda/tests/test_integration/test_orders.py
pyoanda/tests/test_integration/test_position.py
pyoanda/tests/test_integration/test_trade.py
pyoanda/tests/test_integration/test_transaction.py
pyoanda/utils/__init__.py
pyoanda/utils/__init__.pyc
pyoanda/utils/type_checker.py
pyoanda/utils/type_checker.pyc
pyoanda/utils/tests/__init__.py
pyoanda/utils/tests/__init__.pyc
pyoanda/utils/tests/test_type_checker.py
pyoanda/utils/tests/__pycache__/test_type_checker.cpython-27-PYTEST.pyc
PyOanda-1.01.dist-info/DESCRIPTION.rst
PyOanda-1.01.dist-info/METADATA
PyOanda-1.01.dist-info/metadata.json
PyOanda-1.01.dist-info/RECORD
PyOanda-1.01.dist-info/top_level.txt
PyOanda-1.01.dist-info/WHEEL
