Metadata-Version: 2.0
Name: PyOanda
Version: 1.01
Summary: Oanda’s API python wrapper. Robust and Fast API wrapper for your Forex bot Python library that wraps Oanda API. Built on top of requests, it’s easy to use and makes sense.
Requires-Dist: requests
